LICENSE
MANIFEST.in
README
setup.py
rask_raid/__init__.py
rask_raid/handler.py
rask_raid/skernel.py
rask_raid.egg-info/PKG-INFO
rask_raid.egg-info/SOURCES.txt
rask_raid.egg-info/dependency_links.txt
rask_raid.egg-info/requires.txt
rask_raid.egg-info/top_level.txt
rask_raid/actions/__init__.py
rask_raid/actions/welcome.py