Metadata-Version: 1.0
Name: rask-raid
Version: 0.1.0
Summary: Viking Makt WebSocket Protocol
Home-page: https://gitlab.com/vikingmakt/rask_raid
Author: Umgeher Torgersen
Author-email: me@umgeher.org
License: https://gitlab.com/vikingmakt/rask_raid/raw/master/LICENSE
Platform: UNKNOWN
